cloelike/__init__.py
cloelike-0.0.0.dist-info/METADATA
cloelike-0.0.0.dist-info/WHEEL
cloelike-0.0.0.dist-info/RECORD
